{
    "id": 135368643,
    "name": "TAN4",
    "author": "NotChipz",
    "creators": [""],
    "verifier": "Obey",
    "verification": "https://youtu.be/tvXqvB2EWEA",
    "percentToQualify": "100",
    "password": "Free To Copy",
    "records": [
                                {
            "user": "rubiks",
            "link": "https://www.youtube.com/watch?v=7ekozXIN3rs",
            "percent": 100,
            "hz": 480
        },
                                                       {
            "user": "Girg",
            "link": "https://youtu.be/1BiVP5t159c",
            "percent": 100,
            "hz": 480
        }
    ]
}
